country_package/__init__.py
country_package/countries.py
country_package/country.csv
country_package/funzioni_country.py
project1_Militello_Bosco_Passarelli-6.0.0.dist-info/LICENSE.txt
project1_Militello_Bosco_Passarelli-6.0.0.dist-info/METADATA
project1_Militello_Bosco_Passarelli-6.0.0.dist-info/WHEEL
project1_Militello_Bosco_Passarelli-6.0.0.dist-info/top_level.txt
project1_Militello_Bosco_Passarelli-6.0.0.dist-info/RECORD
