Metadata-Version: 2.1
Name: project1-Militello-Bosco-Passarelli
Version: 6.0.0
Summary: Applicativo per semplici calcoli sulla popolazione di 10 paesi del mondo
Home-page: https://gitlab.com/theunusual/2020_assignment1_countries
Author: Patrick Militello, Alessandro Bosco, Raffaello Passarelli
Author-email: p.militello@campus.unimib.it, a.bosco10@campus.unimib.it, r.passarelli@campus.unimib.it
License: UNKNOWN
Platform: UNKNOWN
Classifier: Programming Language :: Python :: 3
